pubmed_types/__init__.py
pubmed_types/models/__init__.py
pubmed_types/models/jats/__init__.py
pubmed_types/models/jats/abbrev_journal_title.py
pubmed_types/models/jats/access_date.py
pubmed_types/models/jats/alt_text.py
pubmed_types/models/jats/app.py
pubmed_types/models/jats/app_group.py
pubmed_types/models/jats/array_orientation.py
pubmed_types/models/jats/article.py
pubmed_types/models/jats/article_categories.py
pubmed_types/models/jats/article_dtd_version.py
pubmed_types/models/jats/article_id.py
pubmed_types/models/jats/article_meta.py
pubmed_types/models/jats/article_version.py
pubmed_types/models/jats/article_version_alternatives.py
pubmed_types/models/jats/author_notes.py
pubmed_types/models/jats/award_desc.py
pubmed_types/models/jats/award_group.py
pubmed_types/models/jats/award_name.py
pubmed_types/models/jats/back.py
pubmed_types/models/jats/body.py
pubmed_types/models/jats/bold_toggle.py
pubmed_types/models/jats/boxed_text_orientation.py
pubmed_types/models/jats/boxed_text_position.py
pubmed_types/models/jats/break_mod.py
pubmed_types/models/jats/chem_struct_wrap_orientation.py
pubmed_types/models/jats/chem_struct_wrap_position.py
pubmed_types/models/jats/city.py
pubmed_types/models/jats/code_executable.py
pubmed_types/models/jats/code_orientation.py
pubmed_types/models/jats/code_position.py
pubmed_types/models/jats/col.py
pubmed_types/models/jats/col_align.py
pubmed_types/models/jats/col_valign.py
pubmed_types/models/jats/colgroup.py
pubmed_types/models/jats/colgroup_align.py
pubmed_types/models/jats/colgroup_valign.py
pubmed_types/models/jats/conf_num.py
pubmed_types/models/jats/conf_theme.py
pubmed_types/models/jats/conference.py
pubmed_types/models/jats/contrib_corresp.py
pubmed_types/models/jats/contrib_deceased.py
pubmed_types/models/jats/contrib_equal_contrib.py
pubmed_types/models/jats/contrib_id.py
pubmed_types/models/jats/contrib_id_authenticated.py
pubmed_types/models/jats/contributed_resource_group.py
pubmed_types-0.2.0.dist-info/LICENSE
pubmed_types-0.2.0.dist-info/METADATA
pubmed_types-0.2.0.dist-info/WHEEL
pubmed_types-0.2.0.dist-info/RECORD
